primap2/__init__.py
primap2/_accessor_base.py
primap2/_aggregate.py
primap2/_convert.py
primap2/_data_format.py
primap2/_dim_names.py
primap2/_downscale.py
primap2/_fill_combine.py
primap2/_merge.py
primap2/_metadata.py
primap2/_overview.py
primap2/_selection.py
primap2/_setters.py
primap2/_types.py
primap2/_units.py
primap2/accessors.py
primap2/csg/__init__.py
primap2/csg/_compose.py
primap2/csg/_models.py
primap2/csg/_wrapper.py
primap2/csg/_strategies/__init__.py
primap2/csg/_strategies/exceptions.py
primap2/csg/_strategies/gaps.py
primap2/csg/_strategies/global_least_squares.py
primap2/csg/_strategies/local_least_squares.py
primap2/csg/_strategies/local_trends.py
primap2/csg/_strategies/substitution.py
primap2/pm2io/_GHG_inventory_reading.py
primap2/pm2io/__init__.py
primap2/pm2io/_conversion.py
primap2/pm2io/_data_reading.py
primap2/pm2io/_interchange_format.py
primap2/tests/__init__.py
primap2/tests/conftest.py
primap2/tests/examples.py
primap2/tests/test_aggregate.py
primap2/tests/test_conversion.py
primap2/tests/test_convert.py
primap2/tests/test_data_format.py
primap2/tests/test_data_reading.py
primap2/tests/test_downscale.py
primap2/tests/test_fill_combine.py
primap2/tests/test_interchange_format.py
primap2/tests/test_merge.py
primap2/tests/test_metadata.py
primap2/tests/test_overview.py
primap2/tests/test_selection.py
primap2/tests/test_setters.py
primap2/tests/test_units.py
primap2/tests/utils.py
primap2/tests/csg/test_compose.py
primap2/tests/csg/test_gaps.py
primap2/tests/csg/test_models.py
primap2/tests/csg/test_strategies.py
primap2/tests/csg/test_wrapper.py
primap2/tests/csg/utils.py
primap2/tests/data/BURDI_conversion.csv
primap2/tests/data/Guetschow-et-al-2021-PRIMAP-crf96_2021-v1.csv
primap2/tests/data/Guetschow-et-al-2021-PRIMAP-crf96_2021-v1.nc
primap2/tests/data/PRIMAP-csg-test.nc
primap2/tests/data/__init__.py
primap2/tests/data/downscale_test_original.nc
primap2/tests/data/long.csv
primap2/tests/data/long_no_time.csv
primap2-0.13.0.dist-info/licenses/LICENSE
primap2-0.13.0.dist-info/METADATA
primap2-0.13.0.dist-info/WHEEL
primap2-0.13.0.dist-info/top_level.txt
primap2-0.13.0.dist-info/RECORD
