Metadata-Version: 2.4
Name: primap2
Version: 0.13.0
Summary: The next generation of the PRIMAP climate policy analysis suite.
Home-page: https://github.com/primap-community/primap2
Author: Mika Pflüger
Author-email: mika.pflueger@climate-resource.com
License: Apache Software License 2.0
Project-URL: Documentation, https://primap2.readthedocs.io/
Classifier: Development Status :: 3 - Alpha
Classifier: Intended Audience :: Science/Research
Classifier: Topic :: Scientific/Engineering :: Atmospheric Science
Classifier: License :: OSI Approved :: Apache Software License
Classifier: Natural Language :: English
Classifier: Programming Language :: Python :: 3
Classifier: Programming Language :: Python :: 3.11
Classifier: Programming Language :: Python :: 3.12
Requires-Python: <3.13,>=3.11
License-File: LICENSE
Requires-Dist: attrs>=23
Requires-Dist: xarray==2025.8.0
Requires-Dist: numbagg>=0.8.1
Requires-Dist: pint>=0.24.4
Requires-Dist: pint_xarray<0.6,>=0.4
Requires-Dist: numpy<2,>=1.26
Requires-Dist: pandas>=2.2.2
Requires-Dist: openscm_units>=0.6
Requires-Dist: loguru>=0.7
Requires-Dist: scipy>=1.13.0
Requires-Dist: h5netcdf>=1
Requires-Dist: h5py>=3.10.0
Requires-Dist: matplotlib>=3.7
Requires-Dist: ruamel.yaml>=0.18
Requires-Dist: strictyaml>=1.7.3
Requires-Dist: openpyxl>=3.1
Requires-Dist: tqdm>=4.66
Requires-Dist: msgpack>=1
Requires-Dist: climate_categories>=0.10.2
Provides-Extra: test
Requires-Dist: pytest>=8; extra == "test"
Requires-Dist: pytest-cov>=4; extra == "test"
Requires-Dist: xdoctest>=1.2; extra == "test"
Provides-Extra: dev
Requires-Dist: tbump>=6.11; extra == "dev"
Requires-Dist: wheel>=0.42; extra == "dev"
Requires-Dist: coverage>=7.4; extra == "dev"
Requires-Dist: Sphinx>=6; extra == "dev"
Requires-Dist: myst-nb>=1; extra == "dev"
Requires-Dist: sphinx-book-theme>=1.1; extra == "dev"
Requires-Dist: sphinx-favicon>=1.0; extra == "dev"
Requires-Dist: jupytext>=1.16; extra == "dev"
Requires-Dist: sphinx-copybutton>=0.5.2; extra == "dev"
Requires-Dist: sphinx-autosummary-accessors>=2023.4; extra == "dev"
Requires-Dist: sphinx-tippy>=0.4.3; extra == "dev"
Requires-Dist: numpydoc>=1.6; extra == "dev"
Requires-Dist: twine>=5; extra == "dev"
Requires-Dist: build>=1.2.2; extra == "dev"
Requires-Dist: pre-commit>=3.6; extra == "dev"
Requires-Dist: pytest>=8; extra == "dev"
Requires-Dist: pytest-cov>=4; extra == "dev"
Requires-Dist: xdoctest>=1.2; extra == "dev"
Requires-Dist: setuptools>=66; extra == "dev"
Requires-Dist: towncrier>=23.6.0; extra == "dev"
Requires-Dist: ipykernel>=6.27.1; extra == "dev"
Requires-Dist: jupyter>=1.1; extra == "dev"
Requires-Dist: mypy>=1.11; extra == "dev"
Requires-Dist: tox>=4.11; extra == "dev"
Requires-Dist: tox-uv>=1.11.3; extra == "dev"
Requires-Dist: ruff>=0.6.3; extra == "dev"
Requires-Dist: ruff-lsp>=0.0.50; extra == "dev"
Provides-Extra: datalad
Requires-Dist: datalad>=1.1; extra == "datalad"
Dynamic: license-file
